<?xml version = '1.0' encoding = 'UTF-8'?><RUN_SET>
   <RUN alias="SC_RUN_11222_1#24" center_name="SC" accession="ERR426469" broker_name="EGA" xmlns:xsi="http://www.w3.org/2001/XMLSchema-instance">
      <IDENTIFIERS>
         <PRIMARY_ID>ERR426469</PRIMARY_ID>
         <SUBMITTER_ID namespace="SC">SC_RUN_11222_1#24</SUBMITTER_ID>
      </IDENTIFIERS>
      <EXPERIMENT_REF refname="SC_EXP_11222_1#24" refcenter="SC" accession="ERX392744">
         <IDENTIFIERS>
            <PRIMARY_ID>ERX392744</PRIMARY_ID>
            <SUBMITTER_ID namespace="SC">SC_EXP_11222_1#24</SUBMITTER_ID>
         </IDENTIFIERS>
      </EXPERIMENT_REF>
      <DATA_BLOCK>
         <FILES>
            <FILE filename="11222_1#24.cram.gpg" filetype="cram" checksum_method="MD5" checksum="972fe76fbad1468fafb2938ff6d9280e" unencrypted_checksum="a5c5fb927806bfa4d7ebe669b216d240"/>
         </FILES>
      </DATA_BLOCK>
   </RUN>
</RUN_SET>