<?xml version = '1.0' encoding = 'UTF-8'?><RUN_SET>
   <RUN alias="SC_RUN_13429_2" center_name="SC" accession="ERR655308" broker_name="EGA" xmlns:xsi="http://www.w3.org/2001/XMLSchema-instance">
      <IDENTIFIERS>
         <PRIMARY_ID>ERR655308</PRIMARY_ID>
         <SUBMITTER_ID namespace="SC">SC_RUN_13429_2</SUBMITTER_ID>
      </IDENTIFIERS>
      <EXPERIMENT_REF refname="SC_EXP_13429_2" refcenter="SC" accession="ERX611631">
         <IDENTIFIERS>
            <PRIMARY_ID>ERX611631</PRIMARY_ID>
            <SUBMITTER_ID namespace="SC">SC_EXP_13429_2</SUBMITTER_ID>
         </IDENTIFIERS>
      </EXPERIMENT_REF>
      <DATA_BLOCK>
         <FILES>
            <FILE filename="13429_2.cram.gpg" filetype="cram" checksum_method="MD5" checksum="a268abce2e1b603d66a1639a253097f9" unencrypted_checksum="ce0d1408c3d195ec9b96d3f7e9cc3d1b"/>
         </FILES>
      </DATA_BLOCK>
   </RUN>
</RUN_SET>