<?xml version = '1.0' encoding = 'UTF-8'?><RUN_SET>
   <RUN alias="SC_RUN_14059_8#3" center_name="SC" accession="ERR838357" broker_name="EGA" xmlns:xsi="http://www.w3.org/2001/XMLSchema-instance">
      <IDENTIFIERS>
         <PRIMARY_ID>ERR838357</PRIMARY_ID>
         <SUBMITTER_ID namespace="SC">SC_RUN_14059_8#3</SUBMITTER_ID>
      </IDENTIFIERS>
      <EXPERIMENT_REF refname="SC_EXP_14059_8#3" refcenter="SC" accession="ERX918444">
         <IDENTIFIERS>
            <PRIMARY_ID>ERX918444</PRIMARY_ID>
            <SUBMITTER_ID namespace="SC">SC_EXP_14059_8#3</SUBMITTER_ID>
         </IDENTIFIERS>
      </EXPERIMENT_REF>
      <DATA_BLOCK>
         <FILES>
            <FILE filename="14059_8#3.cram.gpg" filetype="cram" checksum_method="MD5" checksum="a51a489e52d15ff6d0573e32c3167bd6" unencrypted_checksum="fb5d6802444223273c1da863de49b2b9"/>
         </FILES>
      </DATA_BLOCK>
   </RUN>
</RUN_SET>