<?xml version = '1.0' encoding = 'UTF-8'?><RUN_SET>
   <RUN alias="SC_RUN_10907_1#28" center_name="SC" accession="ERR412180" broker_name="EGA" xmlns:xsi="http://www.w3.org/2001/XMLSchema-instance">
      <IDENTIFIERS>
         <PRIMARY_ID>ERR412180</PRIMARY_ID>
         <SUBMITTER_ID namespace="SC">SC_RUN_10907_1#28</SUBMITTER_ID>
      </IDENTIFIERS>
      <EXPERIMENT_REF refname="SC_EXP_10907_1#28" refcenter="SC" accession="ERX378541">
         <IDENTIFIERS>
            <PRIMARY_ID>ERX378541</PRIMARY_ID>
            <SUBMITTER_ID namespace="SC">SC_EXP_10907_1#28</SUBMITTER_ID>
         </IDENTIFIERS>
      </EXPERIMENT_REF>
      <DATA_BLOCK>
         <FILES>
            <FILE filename="10907_1#28.cram.gpg" filetype="cram" checksum_method="MD5" checksum="c09570f2d9a083d9fd0d2cc25a65a397" unencrypted_checksum="451b032d6af4e3ff62f085adc162deee"/>
         </FILES>
      </DATA_BLOCK>
   </RUN>
</RUN_SET>