<?xml version = '1.0' encoding = 'UTF-8'?><RUN_SET>
   <RUN alias="SC_RUN_14654_1#9" center_name="SC" accession="ERR839398" broker_name="EGA" xmlns:xsi="http://www.w3.org/2001/XMLSchema-instance">
      <IDENTIFIERS>
         <PRIMARY_ID>ERR839398</PRIMARY_ID>
         <SUBMITTER_ID namespace="SC">SC_RUN_14654_1#9</SUBMITTER_ID>
      </IDENTIFIERS>
      <EXPERIMENT_REF refname="SC_EXP_14654_1#9" refcenter="SC" accession="ERX919485">
         <IDENTIFIERS>
            <PRIMARY_ID>ERX919485</PRIMARY_ID>
            <SUBMITTER_ID namespace="SC">SC_EXP_14654_1#9</SUBMITTER_ID>
         </IDENTIFIERS>
      </EXPERIMENT_REF>
      <DATA_BLOCK>
         <FILES>
            <FILE filename="14654_1#9.cram.gpg" filetype="cram" checksum_method="MD5" checksum="f0ed08852bd0f19909351a0d54c45539" unencrypted_checksum="7d1515c33774fc598379ca4d6202c328"/>
         </FILES>
      </DATA_BLOCK>
   </RUN>
</RUN_SET>