<?xml version = '1.0' encoding = 'UTF-8'?><RUN_SET>
   <RUN alias="SC_RUN_11624_1#26" center_name="SC" accession="ERR462239" broker_name="EGA" xmlns:xsi="http://www.w3.org/2001/XMLSchema-instance">
      <IDENTIFIERS>
         <PRIMARY_ID>ERR462239</PRIMARY_ID>
         <SUBMITTER_ID namespace="SC">SC_RUN_11624_1#26</SUBMITTER_ID>
      </IDENTIFIERS>
      <EXPERIMENT_REF refname="SC_EXP_11624_1#26" refcenter="SC" accession="ERX428580">
         <IDENTIFIERS>
            <PRIMARY_ID>ERX428580</PRIMARY_ID>
            <SUBMITTER_ID namespace="SC">SC_EXP_11624_1#26</SUBMITTER_ID>
         </IDENTIFIERS>
      </EXPERIMENT_REF>
      <DATA_BLOCK>
         <FILES>
            <FILE filename="11624_1#26.cram.gpg" filetype="cram" checksum_method="MD5" checksum="1a646f245288719ad53e0d6bbae45292" unencrypted_checksum="8e4a9e23f0cd32becd532ad6b710b43c"/>
         </FILES>
      </DATA_BLOCK>
   </RUN>
</RUN_SET>