<?xml version = '1.0' encoding = 'UTF-8'?><RUN_SET>
   <RUN alias="SC_RUN_12856_1#6" center_name="SC" accession="ERR835186" broker_name="EGA" xmlns:xsi="http://www.w3.org/2001/XMLSchema-instance">
      <IDENTIFIERS>
         <PRIMARY_ID>ERR835186</PRIMARY_ID>
         <SUBMITTER_ID namespace="SC">SC_RUN_12856_1#6</SUBMITTER_ID>
      </IDENTIFIERS>
      <EXPERIMENT_REF refname="SC_EXP_12856_1#6" refcenter="SC" accession="ERX915273">
         <IDENTIFIERS>
            <PRIMARY_ID>ERX915273</PRIMARY_ID>
            <SUBMITTER_ID namespace="SC">SC_EXP_12856_1#6</SUBMITTER_ID>
         </IDENTIFIERS>
      </EXPERIMENT_REF>
      <DATA_BLOCK>
         <FILES>
            <FILE filename="12856_1#6.cram.gpg" filetype="cram" checksum_method="MD5" checksum="d4c2c382d1a27b1e13c7b2fbdc82486e" unencrypted_checksum="81ea1de98fe50393777763d371f86c90"/>
         </FILES>
      </DATA_BLOCK>
   </RUN>
</RUN_SET>