<?xml version = '1.0' encoding = 'UTF-8'?><RUN_SET>
   <RUN alias="SC_RUN_11972_5#21" center_name="SC" accession="ERR494468" broker_name="EGA" xmlns:xsi="http://www.w3.org/2001/XMLSchema-instance">
      <IDENTIFIERS>
         <PRIMARY_ID>ERR494468</PRIMARY_ID>
         <SUBMITTER_ID namespace="SC">SC_RUN_11972_5#21</SUBMITTER_ID>
      </IDENTIFIERS>
      <EXPERIMENT_REF refname="SC_EXP_11972_5#21" refcenter="SC" accession="ERX459884">
         <IDENTIFIERS>
            <PRIMARY_ID>ERX459884</PRIMARY_ID>
            <SUBMITTER_ID namespace="SC">SC_EXP_11972_5#21</SUBMITTER_ID>
         </IDENTIFIERS>
      </EXPERIMENT_REF>
      <DATA_BLOCK>
         <FILES>
            <FILE filename="11972_5#21.cram.gpg" filetype="cram" checksum_method="MD5" checksum="136999ec68a6938c85ba449195140468" unencrypted_checksum="7921e5cda56497bb7109f4643ae3564d"/>
         </FILES>
      </DATA_BLOCK>
   </RUN>
</RUN_SET>