<?xml version = '1.0' encoding = 'UTF-8'?><RUN_SET>
   <RUN alias="SC_RUN_11516_1#52" center_name="SC" accession="ERR436906" broker_name="EGA" xmlns:xsi="http://www.w3.org/2001/XMLSchema-instance">
      <IDENTIFIERS>
         <PRIMARY_ID>ERR436906</PRIMARY_ID>
         <SUBMITTER_ID namespace="SC">SC_RUN_11516_1#52</SUBMITTER_ID>
      </IDENTIFIERS>
      <EXPERIMENT_REF refname="SC_EXP_11516_1#52" refcenter="SC" accession="ERX403569">
         <IDENTIFIERS>
            <PRIMARY_ID>ERX403569</PRIMARY_ID>
            <SUBMITTER_ID namespace="SC">SC_EXP_11516_1#52</SUBMITTER_ID>
         </IDENTIFIERS>
      </EXPERIMENT_REF>
      <DATA_BLOCK>
         <FILES>
            <FILE filename="11516_1#52.cram.gpg" filetype="cram" checksum_method="MD5" checksum="d3a2c5fb4fc1263abe23b54f98120f87" unencrypted_checksum="1cf85aeb07b352fad7c5a4a579e97ed1"/>
         </FILES>
      </DATA_BLOCK>
   </RUN>
</RUN_SET>