<?xml version = '1.0' encoding = 'UTF-8'?><RUN_SET>
   <RUN alias="SC_RUN_13346_2#11" center_name="SC" accession="ERR837441" broker_name="EGA" xmlns:xsi="http://www.w3.org/2001/XMLSchema-instance">
      <IDENTIFIERS>
         <PRIMARY_ID>ERR837441</PRIMARY_ID>
         <SUBMITTER_ID namespace="SC">SC_RUN_13346_2#11</SUBMITTER_ID>
      </IDENTIFIERS>
      <EXPERIMENT_REF refname="SC_EXP_13346_2#11" refcenter="SC" accession="ERX917528">
         <IDENTIFIERS>
            <PRIMARY_ID>ERX917528</PRIMARY_ID>
            <SUBMITTER_ID namespace="SC">SC_EXP_13346_2#11</SUBMITTER_ID>
         </IDENTIFIERS>
      </EXPERIMENT_REF>
      <DATA_BLOCK>
         <FILES>
            <FILE filename="13346_2#11.cram.gpg" filetype="cram" checksum_method="MD5" checksum="dfb2bd38f5658095dd4f5c5c1d641495" unencrypted_checksum="30a36f037525b06de6b16d63f57265df"/>
         </FILES>
      </DATA_BLOCK>
   </RUN>
</RUN_SET>