<?xml version = '1.0' encoding = 'UTF-8'?><RUN_SET>
   <RUN alias="SC_RUN_11688_1#57" center_name="SC" accession="ERR456253" broker_name="EGA" xmlns:xsi="http://www.w3.org/2001/XMLSchema-instance">
      <IDENTIFIERS>
         <PRIMARY_ID>ERR456253</PRIMARY_ID>
         <SUBMITTER_ID namespace="SC">SC_RUN_11688_1#57</SUBMITTER_ID>
      </IDENTIFIERS>
      <EXPERIMENT_REF refname="SC_EXP_11688_1#57" refcenter="SC" accession="ERX422608">
         <IDENTIFIERS>
            <PRIMARY_ID>ERX422608</PRIMARY_ID>
            <SUBMITTER_ID namespace="SC">SC_EXP_11688_1#57</SUBMITTER_ID>
         </IDENTIFIERS>
      </EXPERIMENT_REF>
      <DATA_BLOCK>
         <FILES>
            <FILE filename="11688_1#57.cram.gpg" filetype="cram" checksum_method="MD5" checksum="d5cf5758834a240251ae127f338bb4c5" unencrypted_checksum="a4cb2c4a4ec6415662f8b523e305f8f7"/>
         </FILES>
      </DATA_BLOCK>
   </RUN>
</RUN_SET>