<?xml version = '1.0' encoding = 'UTF-8'?><RUN_SET>
   <RUN alias="SC_RUN_11956_5#24" center_name="SC" accession="ERR492857" broker_name="EGA" xmlns:xsi="http://www.w3.org/2001/XMLSchema-instance">
      <IDENTIFIERS>
         <PRIMARY_ID>ERR492857</PRIMARY_ID>
         <SUBMITTER_ID namespace="SC">SC_RUN_11956_5#24</SUBMITTER_ID>
      </IDENTIFIERS>
      <EXPERIMENT_REF refname="SC_EXP_11956_5#24" refcenter="SC" accession="ERX458311">
         <IDENTIFIERS>
            <PRIMARY_ID>ERX458311</PRIMARY_ID>
            <SUBMITTER_ID namespace="SC">SC_EXP_11956_5#24</SUBMITTER_ID>
         </IDENTIFIERS>
      </EXPERIMENT_REF>
      <DATA_BLOCK>
         <FILES>
            <FILE filename="11956_5#24.cram.gpg" filetype="cram" checksum_method="MD5" checksum="b717d0458fdce5dd10b2a4e2168c6f7e" unencrypted_checksum="390bebc21914758040c91b682de9fce8"/>
         </FILES>
      </DATA_BLOCK>
   </RUN>
</RUN_SET>