<?xml version = '1.0' encoding = 'UTF-8'?><RUN_SET>
   <RUN alias="SC_RUN_12680_1#17" center_name="SC" accession="ERR834481" broker_name="EGA" xmlns:xsi="http://www.w3.org/2001/XMLSchema-instance">
      <IDENTIFIERS>
         <PRIMARY_ID>ERR834481</PRIMARY_ID>
         <SUBMITTER_ID namespace="SC">SC_RUN_12680_1#17</SUBMITTER_ID>
      </IDENTIFIERS>
      <EXPERIMENT_REF refname="SC_EXP_12680_1#17" refcenter="SC" accession="ERX914568">
         <IDENTIFIERS>
            <PRIMARY_ID>ERX914568</PRIMARY_ID>
            <SUBMITTER_ID namespace="SC">SC_EXP_12680_1#17</SUBMITTER_ID>
         </IDENTIFIERS>
      </EXPERIMENT_REF>
      <DATA_BLOCK>
         <FILES>
            <FILE filename="12680_1#17.cram.gpg" filetype="cram" checksum_method="MD5" checksum="3521abf6291fba3a80fac2d846caf82e" unencrypted_checksum="7e1a2a8e53d5a2b2c9b7e0cc1f6feb6e"/>
         </FILES>
      </DATA_BLOCK>
   </RUN>
</RUN_SET>