<?xml version = '1.0' encoding = 'UTF-8'?><RUN_SET>
   <RUN alias="SC_RUN_11056_6#52" center_name="SC" accession="ERR420638" broker_name="EGA" xmlns:xsi="http://www.w3.org/2001/XMLSchema-instance">
      <IDENTIFIERS>
         <PRIMARY_ID>ERR420638</PRIMARY_ID>
         <SUBMITTER_ID namespace="SC">SC_RUN_11056_6#52</SUBMITTER_ID>
      </IDENTIFIERS>
      <EXPERIMENT_REF refname="SC_EXP_11056_6#52" refcenter="SC" accession="ERX386931">
         <IDENTIFIERS>
            <PRIMARY_ID>ERX386931</PRIMARY_ID>
            <SUBMITTER_ID namespace="SC">SC_EXP_11056_6#52</SUBMITTER_ID>
         </IDENTIFIERS>
      </EXPERIMENT_REF>
      <DATA_BLOCK>
         <FILES>
            <FILE filename="11056_6#52.cram.gpg" filetype="cram" checksum_method="MD5" checksum="5421e5c0097017b1a12433abd054aeea" unencrypted_checksum="4f26f852b265f39cf0775227021f9a53"/>
         </FILES>
      </DATA_BLOCK>
   </RUN>
</RUN_SET>