<?xml version = '1.0' encoding = 'UTF-8'?><RUN_SET>
   <RUN alias="SC_RUN_11623_1#29" center_name="SC" accession="ERR455775" broker_name="EGA" xmlns:xsi="http://www.w3.org/2001/XMLSchema-instance">
      <IDENTIFIERS>
         <PRIMARY_ID>ERR455775</PRIMARY_ID>
         <SUBMITTER_ID namespace="SC">SC_RUN_11623_1#29</SUBMITTER_ID>
      </IDENTIFIERS>
      <EXPERIMENT_REF refname="SC_EXP_11623_1#29" refcenter="SC" accession="ERX422130">
         <IDENTIFIERS>
            <PRIMARY_ID>ERX422130</PRIMARY_ID>
            <SUBMITTER_ID namespace="SC">SC_EXP_11623_1#29</SUBMITTER_ID>
         </IDENTIFIERS>
      </EXPERIMENT_REF>
      <DATA_BLOCK>
         <FILES>
            <FILE filename="11623_1#29.cram.gpg" filetype="cram" checksum_method="MD5" checksum="b51a416b955711916f2aa4e5b96c098d" unencrypted_checksum="1465a8cb7f749ffeda32a0184ef11d8e"/>
         </FILES>
      </DATA_BLOCK>
   </RUN>
</RUN_SET>