<?xml version = '1.0' encoding = 'UTF-8'?><RUN_SET>
   <RUN alias="SC_RUN_11952_4#6" center_name="SC" accession="ERR492716" broker_name="EGA" xmlns:xsi="http://www.w3.org/2001/XMLSchema-instance">
      <IDENTIFIERS>
         <PRIMARY_ID>ERR492716</PRIMARY_ID>
         <SUBMITTER_ID namespace="SC">SC_RUN_11952_4#6</SUBMITTER_ID>
      </IDENTIFIERS>
      <EXPERIMENT_REF refname="SC_EXP_11952_4#6" refcenter="SC" accession="ERX458170">
         <IDENTIFIERS>
            <PRIMARY_ID>ERX458170</PRIMARY_ID>
            <SUBMITTER_ID namespace="SC">SC_EXP_11952_4#6</SUBMITTER_ID>
         </IDENTIFIERS>
      </EXPERIMENT_REF>
      <DATA_BLOCK>
         <FILES>
            <FILE filename="11952_4#6.cram.gpg" filetype="cram" checksum_method="MD5" checksum="39adbcf42eb3d4aa6dc47a32a1b29e18" unencrypted_checksum="1a9c082023a04b27e6c82ac4fb999a40"/>
         </FILES>
      </DATA_BLOCK>
   </RUN>
</RUN_SET>