<?xml version = '1.0' encoding = 'UTF-8'?><RUN_SET>
   <RUN alias="SC_RUN_10905_4#47" center_name="SC" accession="ERR412102" broker_name="EGA" xmlns:xsi="http://www.w3.org/2001/XMLSchema-instance">
      <IDENTIFIERS>
         <PRIMARY_ID>ERR412102</PRIMARY_ID>
         <SUBMITTER_ID namespace="SC">SC_RUN_10905_4#47</SUBMITTER_ID>
      </IDENTIFIERS>
      <EXPERIMENT_REF refname="SC_EXP_10905_4#47" refcenter="SC" accession="ERX378463">
         <IDENTIFIERS>
            <PRIMARY_ID>ERX378463</PRIMARY_ID>
            <SUBMITTER_ID namespace="SC">SC_EXP_10905_4#47</SUBMITTER_ID>
         </IDENTIFIERS>
      </EXPERIMENT_REF>
      <DATA_BLOCK>
         <FILES>
            <FILE filename="10905_4#47.cram.gpg" filetype="cram" checksum_method="MD5" checksum="3b713674c6a289fde9ed1b8b06a92a71" unencrypted_checksum="f6343fd6ac78ada634351a34a5959681"/>
         </FILES>
      </DATA_BLOCK>
   </RUN>
</RUN_SET>