<?xml version = '1.0' encoding = 'UTF-8'?><RUN_SET>
   <RUN alias="SC_RUN_10922_1#51" center_name="SC" accession="ERR412238" broker_name="EGA" xmlns:xsi="http://www.w3.org/2001/XMLSchema-instance">
      <IDENTIFIERS>
         <PRIMARY_ID>ERR412238</PRIMARY_ID>
         <SUBMITTER_ID namespace="SC">SC_RUN_10922_1#51</SUBMITTER_ID>
      </IDENTIFIERS>
      <EXPERIMENT_REF refname="SC_EXP_10922_1#51" refcenter="SC" accession="ERX378599">
         <IDENTIFIERS>
            <PRIMARY_ID>ERX378599</PRIMARY_ID>
            <SUBMITTER_ID namespace="SC">SC_EXP_10922_1#51</SUBMITTER_ID>
         </IDENTIFIERS>
      </EXPERIMENT_REF>
      <DATA_BLOCK>
         <FILES>
            <FILE filename="10922_1#51.cram.gpg" filetype="cram" checksum_method="MD5" checksum="6f22937a12ad954081c7826051265841" unencrypted_checksum="d57ccad6defda343cc2f4780e512507d"/>
         </FILES>
      </DATA_BLOCK>
   </RUN>
</RUN_SET>