<?xml version = '1.0' encoding = 'UTF-8'?><RUN_SET>
   <RUN alias="SC_RUN_14082_7#27" center_name="SC" accession="ERR838580" broker_name="EGA" xmlns:xsi="http://www.w3.org/2001/XMLSchema-instance">
      <IDENTIFIERS>
         <PRIMARY_ID>ERR838580</PRIMARY_ID>
         <SUBMITTER_ID namespace="SC">SC_RUN_14082_7#27</SUBMITTER_ID>
      </IDENTIFIERS>
      <EXPERIMENT_REF refname="SC_EXP_14082_7#27" refcenter="SC" accession="ERX918667">
         <IDENTIFIERS>
            <PRIMARY_ID>ERX918667</PRIMARY_ID>
            <SUBMITTER_ID namespace="SC">SC_EXP_14082_7#27</SUBMITTER_ID>
         </IDENTIFIERS>
      </EXPERIMENT_REF>
      <DATA_BLOCK>
         <FILES>
            <FILE filename="14082_7#27.cram.gpg" filetype="cram" checksum_method="MD5" checksum="3bcd8ee3bbcde78d35dbf9783adac082" unencrypted_checksum="c50d046b7f4102d8cfa921dc8699d933"/>
         </FILES>
      </DATA_BLOCK>
   </RUN>
</RUN_SET>