<?xml version = '1.0' encoding = 'UTF-8'?><RUN_SET>
   <RUN alias="SC_RUN_13011_2#7" center_name="SC" accession="ERR835812" broker_name="EGA" xmlns:xsi="http://www.w3.org/2001/XMLSchema-instance">
      <IDENTIFIERS>
         <PRIMARY_ID>ERR835812</PRIMARY_ID>
         <SUBMITTER_ID namespace="SC">SC_RUN_13011_2#7</SUBMITTER_ID>
      </IDENTIFIERS>
      <EXPERIMENT_REF refname="SC_EXP_13011_2#7" refcenter="SC" accession="ERX915899">
         <IDENTIFIERS>
            <PRIMARY_ID>ERX915899</PRIMARY_ID>
            <SUBMITTER_ID namespace="SC">SC_EXP_13011_2#7</SUBMITTER_ID>
         </IDENTIFIERS>
      </EXPERIMENT_REF>
      <DATA_BLOCK>
         <FILES>
            <FILE filename="13011_2#7.cram.gpg" filetype="cram" checksum_method="MD5" checksum="217e843dd1ea95871cbaddb3c3f8ef72" unencrypted_checksum="c3e5b32bf17b8b4a691c6e3f1f4f7cb5"/>
         </FILES>
      </DATA_BLOCK>
   </RUN>
</RUN_SET>