<?xml version = '1.0' encoding = 'UTF-8'?><RUN_SET>
   <RUN alias="SC_RUN_10832_7#26" center_name="SC" accession="ERR408268" broker_name="EGA" xmlns:xsi="http://www.w3.org/2001/XMLSchema-instance">
      <IDENTIFIERS>
         <PRIMARY_ID>ERR408268</PRIMARY_ID>
         <SUBMITTER_ID namespace="SC">SC_RUN_10832_7#26</SUBMITTER_ID>
      </IDENTIFIERS>
      <EXPERIMENT_REF refname="SC_EXP_10832_7#26" refcenter="SC" accession="ERX374629">
         <IDENTIFIERS>
            <PRIMARY_ID>ERX374629</PRIMARY_ID>
            <SUBMITTER_ID namespace="SC">SC_EXP_10832_7#26</SUBMITTER_ID>
         </IDENTIFIERS>
      </EXPERIMENT_REF>
      <DATA_BLOCK>
         <FILES>
            <FILE filename="10832_7#26.cram.gpg" filetype="cram" checksum_method="MD5" checksum="3033ac48625731efeef76beb408474b9" unencrypted_checksum="8cb20eff2c2bc11855f5c5b71f106e3b"/>
         </FILES>
      </DATA_BLOCK>
   </RUN>
</RUN_SET>