<?xml version = '1.0' encoding = 'UTF-8'?><RUN_SET>
   <RUN alias="SC_RUN_11659_2#39" center_name="SC" accession="ERR456037" broker_name="EGA" xmlns:xsi="http://www.w3.org/2001/XMLSchema-instance">
      <IDENTIFIERS>
         <PRIMARY_ID>ERR456037</PRIMARY_ID>
         <SUBMITTER_ID namespace="SC">SC_RUN_11659_2#39</SUBMITTER_ID>
      </IDENTIFIERS>
      <EXPERIMENT_REF refname="SC_EXP_11659_2#39" refcenter="SC" accession="ERX422392">
         <IDENTIFIERS>
            <PRIMARY_ID>ERX422392</PRIMARY_ID>
            <SUBMITTER_ID namespace="SC">SC_EXP_11659_2#39</SUBMITTER_ID>
         </IDENTIFIERS>
      </EXPERIMENT_REF>
      <DATA_BLOCK>
         <FILES>
            <FILE filename="11659_2#39.cram.gpg" filetype="cram" checksum_method="MD5" checksum="d4b8300ffa481c3ee1312cc3554311a7" unencrypted_checksum="24bb54daa92d6c720490944bf59be25f"/>
         </FILES>
      </DATA_BLOCK>
   </RUN>
</RUN_SET>