<?xml version = '1.0' encoding = 'UTF-8'?><RUN_SET>
   <RUN alias="SC_RUN_13937_3#40" center_name="SC" accession="ERR838110" broker_name="EGA" xmlns:xsi="http://www.w3.org/2001/XMLSchema-instance">
      <IDENTIFIERS>
         <PRIMARY_ID>ERR838110</PRIMARY_ID>
         <SUBMITTER_ID namespace="SC">SC_RUN_13937_3#40</SUBMITTER_ID>
      </IDENTIFIERS>
      <EXPERIMENT_REF refname="SC_EXP_13937_3#40" refcenter="SC" accession="ERX918197">
         <IDENTIFIERS>
            <PRIMARY_ID>ERX918197</PRIMARY_ID>
            <SUBMITTER_ID namespace="SC">SC_EXP_13937_3#40</SUBMITTER_ID>
         </IDENTIFIERS>
      </EXPERIMENT_REF>
      <DATA_BLOCK>
         <FILES>
            <FILE filename="13937_3#40.cram.gpg" filetype="cram" checksum_method="MD5" checksum="8027ad55246792cfc022f7572bddc5bc" unencrypted_checksum="bebf6bb1309b98a23fdb5107f8e1cc2c"/>
         </FILES>
      </DATA_BLOCK>
   </RUN>
</RUN_SET>