<?xml version = '1.0' encoding = 'UTF-8'?><RUN_SET>
   <RUN alias="SC_RUN_14655_1#8" center_name="SC" accession="ERR839415" broker_name="EGA" xmlns:xsi="http://www.w3.org/2001/XMLSchema-instance">
      <IDENTIFIERS>
         <PRIMARY_ID>ERR839415</PRIMARY_ID>
         <SUBMITTER_ID namespace="SC">SC_RUN_14655_1#8</SUBMITTER_ID>
      </IDENTIFIERS>
      <EXPERIMENT_REF refname="SC_EXP_14655_1#8" refcenter="SC" accession="ERX919502">
         <IDENTIFIERS>
            <PRIMARY_ID>ERX919502</PRIMARY_ID>
            <SUBMITTER_ID namespace="SC">SC_EXP_14655_1#8</SUBMITTER_ID>
         </IDENTIFIERS>
      </EXPERIMENT_REF>
      <DATA_BLOCK>
         <FILES>
            <FILE filename="14655_1#8.cram.gpg" filetype="cram" checksum_method="MD5" checksum="5baf4ee6d3c695f905d297a743af3221" unencrypted_checksum="bb0ffb18a8cdb5972d7b156379856994"/>
         </FILES>
      </DATA_BLOCK>
   </RUN>
</RUN_SET>