<?xml version = '1.0' encoding = 'UTF-8'?><RUN_SET>
   <RUN alias="SC_RUN_11077_7#52" center_name="SC" accession="ERR420701" broker_name="EGA" xmlns:xsi="http://www.w3.org/2001/XMLSchema-instance">
      <IDENTIFIERS>
         <PRIMARY_ID>ERR420701</PRIMARY_ID>
         <SUBMITTER_ID namespace="SC">SC_RUN_11077_7#52</SUBMITTER_ID>
      </IDENTIFIERS>
      <EXPERIMENT_REF refname="SC_EXP_11077_7#52" refcenter="SC" accession="ERX386994">
         <IDENTIFIERS>
            <PRIMARY_ID>ERX386994</PRIMARY_ID>
            <SUBMITTER_ID namespace="SC">SC_EXP_11077_7#52</SUBMITTER_ID>
         </IDENTIFIERS>
      </EXPERIMENT_REF>
      <DATA_BLOCK>
         <FILES>
            <FILE filename="11077_7#52.cram.gpg" filetype="cram" checksum_method="MD5" checksum="2cd09ee685aaaf2be61f5c7c40e83e4c" unencrypted_checksum="471ead0af45d3971ab45766d38b0d056"/>
         </FILES>
      </DATA_BLOCK>
   </RUN>
</RUN_SET>