<?xml version = '1.0' encoding = 'UTF-8'?><RUN_SET>
   <RUN alias="SC_RUN_12831_1#6" center_name="SC" accession="ERR835078" broker_name="EGA" xmlns:xsi="http://www.w3.org/2001/XMLSchema-instance">
      <IDENTIFIERS>
         <PRIMARY_ID>ERR835078</PRIMARY_ID>
         <SUBMITTER_ID namespace="SC">SC_RUN_12831_1#6</SUBMITTER_ID>
      </IDENTIFIERS>
      <EXPERIMENT_REF refname="SC_EXP_12831_1#6" refcenter="SC" accession="ERX915165">
         <IDENTIFIERS>
            <PRIMARY_ID>ERX915165</PRIMARY_ID>
            <SUBMITTER_ID namespace="SC">SC_EXP_12831_1#6</SUBMITTER_ID>
         </IDENTIFIERS>
      </EXPERIMENT_REF>
      <DATA_BLOCK>
         <FILES>
            <FILE filename="12831_1#6.cram.gpg" filetype="cram" checksum_method="MD5" checksum="836d5cf015d6e43e018cfc2902952670" unencrypted_checksum="dda65b19642a18f1b49cb324163ab5d6"/>
         </FILES>
      </DATA_BLOCK>
   </RUN>
</RUN_SET>