<?xml version = '1.0' encoding = 'UTF-8'?><RUN_SET>
   <RUN alias="SC_RUN_11342_2#10" center_name="SC" accession="ERR427534" broker_name="EGA" xmlns:xsi="http://www.w3.org/2001/XMLSchema-instance">
      <IDENTIFIERS>
         <PRIMARY_ID>ERR427534</PRIMARY_ID>
         <SUBMITTER_ID namespace="SC">SC_RUN_11342_2#10</SUBMITTER_ID>
      </IDENTIFIERS>
      <EXPERIMENT_REF refname="SC_EXP_11342_2#10" refcenter="SC" accession="ERX393809">
         <IDENTIFIERS>
            <PRIMARY_ID>ERX393809</PRIMARY_ID>
            <SUBMITTER_ID namespace="SC">SC_EXP_11342_2#10</SUBMITTER_ID>
         </IDENTIFIERS>
      </EXPERIMENT_REF>
      <DATA_BLOCK>
         <FILES>
            <FILE filename="11342_2#10.cram.gpg" filetype="cram" checksum_method="MD5" checksum="a733bd9f416535ab4ef35afbd8966dfa" unencrypted_checksum="4559e10797bbf357bdcd9b3ba49f31b9"/>
         </FILES>
      </DATA_BLOCK>
   </RUN>
</RUN_SET>