<?xml version = '1.0' encoding = 'UTF-8'?><RUN_SET>
   <RUN alias="SC_RUN_11958_8#14" center_name="SC" accession="ERR492951" broker_name="EGA" xmlns:xsi="http://www.w3.org/2001/XMLSchema-instance">
      <IDENTIFIERS>
         <PRIMARY_ID>ERR492951</PRIMARY_ID>
         <SUBMITTER_ID namespace="SC">SC_RUN_11958_8#14</SUBMITTER_ID>
      </IDENTIFIERS>
      <EXPERIMENT_REF refname="SC_EXP_11958_8#14" refcenter="SC" accession="ERX458405">
         <IDENTIFIERS>
            <PRIMARY_ID>ERX458405</PRIMARY_ID>
            <SUBMITTER_ID namespace="SC">SC_EXP_11958_8#14</SUBMITTER_ID>
         </IDENTIFIERS>
      </EXPERIMENT_REF>
      <DATA_BLOCK>
         <FILES>
            <FILE filename="11958_8#14.cram.gpg" filetype="cram" checksum_method="MD5" checksum="fa322daffa70959d72df0c05307c6158" unencrypted_checksum="fbf9be77d5f6a807d07d365145d99865"/>
         </FILES>
      </DATA_BLOCK>
   </RUN>
</RUN_SET>