<?xml version = '1.0' encoding = 'UTF-8'?><RUN_SET>
   <RUN alias="SC_RUN_11197_2#35" center_name="SC" accession="ERR420953" broker_name="EGA" xmlns:xsi="http://www.w3.org/2001/XMLSchema-instance">
      <IDENTIFIERS>
         <PRIMARY_ID>ERR420953</PRIMARY_ID>
         <SUBMITTER_ID namespace="SC">SC_RUN_11197_2#35</SUBMITTER_ID>
      </IDENTIFIERS>
      <EXPERIMENT_REF refname="SC_EXP_11197_2#35" refcenter="SC" accession="ERX387246">
         <IDENTIFIERS>
            <PRIMARY_ID>ERX387246</PRIMARY_ID>
            <SUBMITTER_ID namespace="SC">SC_EXP_11197_2#35</SUBMITTER_ID>
         </IDENTIFIERS>
      </EXPERIMENT_REF>
      <DATA_BLOCK>
         <FILES>
            <FILE filename="11197_2#35.cram.gpg" filetype="cram" checksum_method="MD5" checksum="1bf6228211e2d392a4a663847be2b5bf" unencrypted_checksum="7147398b48794e997cce1a5759292e77"/>
         </FILES>
      </DATA_BLOCK>
   </RUN>
</RUN_SET>