<?xml version = '1.0' encoding = 'UTF-8'?><RUN_SET>
   <RUN alias="SC_RUN_10833_7#56" center_name="SC" accession="ERR408300" broker_name="EGA" xmlns:xsi="http://www.w3.org/2001/XMLSchema-instance">
      <IDENTIFIERS>
         <PRIMARY_ID>ERR408300</PRIMARY_ID>
         <SUBMITTER_ID namespace="SC">SC_RUN_10833_7#56</SUBMITTER_ID>
      </IDENTIFIERS>
      <EXPERIMENT_REF refname="SC_EXP_10833_7#56" refcenter="SC" accession="ERX374661">
         <IDENTIFIERS>
            <PRIMARY_ID>ERX374661</PRIMARY_ID>
            <SUBMITTER_ID namespace="SC">SC_EXP_10833_7#56</SUBMITTER_ID>
         </IDENTIFIERS>
      </EXPERIMENT_REF>
      <DATA_BLOCK>
         <FILES>
            <FILE filename="10833_7#56.cram.gpg" filetype="cram" checksum_method="MD5" checksum="bdb0de6be814d7a69055cc81eb963264" unencrypted_checksum="41accf598a213dd54c5816b633d39744"/>
         </FILES>
      </DATA_BLOCK>
   </RUN>
</RUN_SET>