<?xml version = '1.0' encoding = 'UTF-8'?><RUN_SET>
   <RUN alias="SC_RUN_10783_2#26" center_name="SC" accession="ERR401434" broker_name="EGA" xmlns:xsi="http://www.w3.org/2001/XMLSchema-instance">
      <IDENTIFIERS>
         <PRIMARY_ID>ERR401434</PRIMARY_ID>
         <SUBMITTER_ID namespace="SC">SC_RUN_10783_2#26</SUBMITTER_ID>
      </IDENTIFIERS>
      <EXPERIMENT_REF refname="SC_EXP_10783_2#26" refcenter="SC" accession="ERX367795">
         <IDENTIFIERS>
            <PRIMARY_ID>ERX367795</PRIMARY_ID>
            <SUBMITTER_ID namespace="SC">SC_EXP_10783_2#26</SUBMITTER_ID>
         </IDENTIFIERS>
      </EXPERIMENT_REF>
      <DATA_BLOCK>
         <FILES>
            <FILE filename="10783_2#26.cram.gpg" filetype="cram" checksum_method="MD5" checksum="7d9acbffa4d20fcd3a84c84b6e051da5" unencrypted_checksum="117f5b119c67dd6a6ebc2402f9e52c89"/>
         </FILES>
      </DATA_BLOCK>
   </RUN>
</RUN_SET>