<?xml version = '1.0' encoding = 'UTF-8'?><RUN_SET>
   <RUN alias="SC_RUN_12674_3#34" center_name="SC" accession="ERR569808" broker_name="EGA" xmlns:xsi="http://www.w3.org/2001/XMLSchema-instance">
      <IDENTIFIERS>
         <PRIMARY_ID>ERR569808</PRIMARY_ID>
         <SUBMITTER_ID namespace="SC">SC_RUN_12674_3#34</SUBMITTER_ID>
      </IDENTIFIERS>
      <EXPERIMENT_REF refname="SC_EXP_12674_3#34" refcenter="SC" accession="ERX528797">
         <IDENTIFIERS>
            <PRIMARY_ID>ERX528797</PRIMARY_ID>
            <SUBMITTER_ID namespace="SC">SC_EXP_12674_3#34</SUBMITTER_ID>
         </IDENTIFIERS>
      </EXPERIMENT_REF>
      <DATA_BLOCK>
         <FILES>
            <FILE filename="12674_3#34.cram.gpg" filetype="cram" checksum_method="MD5" checksum="20a1ac1f4f2e10e20fc6aa5b330d5a60" unencrypted_checksum="9e2e491526dab5a0d42aada42903064d"/>
         </FILES>
      </DATA_BLOCK>
   </RUN>
</RUN_SET>