<?xml version = '1.0' encoding = 'UTF-8'?><RUN_SET>
   <RUN alias="SC_RUN_10677_4#11" center_name="SC" accession="ERR389879" broker_name="EGA" xmlns:xsi="http://www.w3.org/2001/XMLSchema-instance">
      <IDENTIFIERS>
         <PRIMARY_ID>ERR389879</PRIMARY_ID>
         <SUBMITTER_ID namespace="SC">SC_RUN_10677_4#11</SUBMITTER_ID>
      </IDENTIFIERS>
      <EXPERIMENT_REF refname="SC_EXP_10677_4#11" refcenter="SC" accession="ERX362109">
         <IDENTIFIERS>
            <PRIMARY_ID>ERX362109</PRIMARY_ID>
            <SUBMITTER_ID namespace="SC">SC_EXP_10677_4#11</SUBMITTER_ID>
         </IDENTIFIERS>
      </EXPERIMENT_REF>
      <DATA_BLOCK>
         <FILES>
            <FILE filename="10677_4#11.cram.gpg" filetype="cram" checksum_method="MD5" checksum="9c3e37739dcb6c4ad55b1f2b9470e20a" unencrypted_checksum="0a8c7824406477dd07b7e5545fff23a1"/>
         </FILES>
      </DATA_BLOCK>
   </RUN>
</RUN_SET>