<?xml version = '1.0' encoding = 'UTF-8'?><RUN_SET>
   <RUN alias="SC_RUN_13056_2#12" center_name="SC" accession="ERR836008" broker_name="EGA" xmlns:xsi="http://www.w3.org/2001/XMLSchema-instance">
      <IDENTIFIERS>
         <PRIMARY_ID>ERR836008</PRIMARY_ID>
         <SUBMITTER_ID namespace="SC">SC_RUN_13056_2#12</SUBMITTER_ID>
      </IDENTIFIERS>
      <EXPERIMENT_REF refname="SC_EXP_13056_2#12" refcenter="SC" accession="ERX916095">
         <IDENTIFIERS>
            <PRIMARY_ID>ERX916095</PRIMARY_ID>
            <SUBMITTER_ID namespace="SC">SC_EXP_13056_2#12</SUBMITTER_ID>
         </IDENTIFIERS>
      </EXPERIMENT_REF>
      <DATA_BLOCK>
         <FILES>
            <FILE filename="13056_2#12.cram.gpg" filetype="cram" checksum_method="MD5" checksum="7e718e409f80ad81531eaa21ae899fe7" unencrypted_checksum="d4ed1086fba6af78ff53b1c6473a9760"/>
         </FILES>
      </DATA_BLOCK>
   </RUN>
</RUN_SET>