<?xml version = '1.0' encoding = 'UTF-8'?><RUN_SET>
   <RUN alias="SC_RUN_12720_1#10" center_name="SC" accession="ERR834601" broker_name="EGA" xmlns:xsi="http://www.w3.org/2001/XMLSchema-instance">
      <IDENTIFIERS>
         <PRIMARY_ID>ERR834601</PRIMARY_ID>
         <SUBMITTER_ID namespace="SC">SC_RUN_12720_1#10</SUBMITTER_ID>
      </IDENTIFIERS>
      <EXPERIMENT_REF refname="SC_EXP_12720_1#10" refcenter="SC" accession="ERX914688">
         <IDENTIFIERS>
            <PRIMARY_ID>ERX914688</PRIMARY_ID>
            <SUBMITTER_ID namespace="SC">SC_EXP_12720_1#10</SUBMITTER_ID>
         </IDENTIFIERS>
      </EXPERIMENT_REF>
      <DATA_BLOCK>
         <FILES>
            <FILE filename="12720_1#10.cram.gpg" filetype="cram" checksum_method="MD5" checksum="a0bf68ef7b9bc8d3eaabf44d8bf82fe3" unencrypted_checksum="01828e604f6218759615cf14ab32b830"/>
         </FILES>
      </DATA_BLOCK>
   </RUN>
</RUN_SET>