<?xml version = '1.0' encoding = 'UTF-8'?><RUN_SET>
   <RUN alias="SC_RUN_13992_1#20" center_name="SC" accession="ERR838231" broker_name="EGA" xmlns:xsi="http://www.w3.org/2001/XMLSchema-instance">
      <IDENTIFIERS>
         <PRIMARY_ID>ERR838231</PRIMARY_ID>
         <SUBMITTER_ID namespace="SC">SC_RUN_13992_1#20</SUBMITTER_ID>
      </IDENTIFIERS>
      <EXPERIMENT_REF refname="SC_EXP_13992_1#20" refcenter="SC" accession="ERX918318">
         <IDENTIFIERS>
            <PRIMARY_ID>ERX918318</PRIMARY_ID>
            <SUBMITTER_ID namespace="SC">SC_EXP_13992_1#20</SUBMITTER_ID>
         </IDENTIFIERS>
      </EXPERIMENT_REF>
      <DATA_BLOCK>
         <FILES>
            <FILE filename="13992_1#20.cram.gpg" filetype="cram" checksum_method="MD5" checksum="e6748ba4adaed06aa278e1b12c52a508" unencrypted_checksum="bcccf819f98105c3630b508e498cc140"/>
         </FILES>
      </DATA_BLOCK>
   </RUN>
</RUN_SET>