<?xml version = '1.0' encoding = 'UTF-8'?><RUN_SET>
   <RUN alias="SC_RUN_12777_1#4" center_name="SC" accession="ERR834934" broker_name="EGA" xmlns:xsi="http://www.w3.org/2001/XMLSchema-instance">
      <IDENTIFIERS>
         <PRIMARY_ID>ERR834934</PRIMARY_ID>
         <SUBMITTER_ID namespace="SC">SC_RUN_12777_1#4</SUBMITTER_ID>
      </IDENTIFIERS>
      <EXPERIMENT_REF refname="SC_EXP_12777_1#4" refcenter="SC" accession="ERX915021">
         <IDENTIFIERS>
            <PRIMARY_ID>ERX915021</PRIMARY_ID>
            <SUBMITTER_ID namespace="SC">SC_EXP_12777_1#4</SUBMITTER_ID>
         </IDENTIFIERS>
      </EXPERIMENT_REF>
      <DATA_BLOCK>
         <FILES>
            <FILE filename="12777_1#4.cram.gpg" filetype="cram" checksum_method="MD5" checksum="81bd012925eea7711d55b4e9157fc718" unencrypted_checksum="f74c306e8879f6d9621a3fd38a1f3145"/>
         </FILES>
      </DATA_BLOCK>
   </RUN>
</RUN_SET>