<?xml version = '1.0' encoding = 'UTF-8'?><RUN_SET>
   <RUN alias="SC_RUN_13900_7#2" center_name="SC" accession="ERR837949" broker_name="EGA" xmlns:xsi="http://www.w3.org/2001/XMLSchema-instance">
      <IDENTIFIERS>
         <PRIMARY_ID>ERR837949</PRIMARY_ID>
         <SUBMITTER_ID namespace="SC">SC_RUN_13900_7#2</SUBMITTER_ID>
      </IDENTIFIERS>
      <EXPERIMENT_REF refname="SC_EXP_13900_7#2" refcenter="SC" accession="ERX918036">
         <IDENTIFIERS>
            <PRIMARY_ID>ERX918036</PRIMARY_ID>
            <SUBMITTER_ID namespace="SC">SC_EXP_13900_7#2</SUBMITTER_ID>
         </IDENTIFIERS>
      </EXPERIMENT_REF>
      <DATA_BLOCK>
         <FILES>
            <FILE filename="13900_7#2.cram.gpg" filetype="cram" checksum_method="MD5" checksum="2ae74fe2ccf25414c6da9ccd928785fd" unencrypted_checksum="e14dc87c228d32ecc6fb495a69fe80f2"/>
         </FILES>
      </DATA_BLOCK>
   </RUN>
</RUN_SET>