<?xml version = '1.0' encoding = 'UTF-8'?><RUN_SET>
   <RUN alias="SC_RUN_13202_1#23" center_name="SC" accession="ERR836829" broker_name="EGA" xmlns:xsi="http://www.w3.org/2001/XMLSchema-instance">
      <IDENTIFIERS>
         <PRIMARY_ID>ERR836829</PRIMARY_ID>
         <SUBMITTER_ID namespace="SC">SC_RUN_13202_1#23</SUBMITTER_ID>
      </IDENTIFIERS>
      <EXPERIMENT_REF refname="SC_EXP_13202_1#23" refcenter="SC" accession="ERX916916">
         <IDENTIFIERS>
            <PRIMARY_ID>ERX916916</PRIMARY_ID>
            <SUBMITTER_ID namespace="SC">SC_EXP_13202_1#23</SUBMITTER_ID>
         </IDENTIFIERS>
      </EXPERIMENT_REF>
      <DATA_BLOCK>
         <FILES>
            <FILE filename="13202_1#23.cram.gpg" filetype="cram" checksum_method="MD5" checksum="8f3c0c3f921499fbddd3e3fd59de9bb0" unencrypted_checksum="5e7349307d172384dc5e6038390afedb"/>
         </FILES>
      </DATA_BLOCK>
   </RUN>
</RUN_SET>