<?xml version = '1.0' encoding = 'UTF-8'?><RUN_SET>
   <RUN alias="SC_RUN_14780_2#6" center_name="SC" accession="ERR839830" broker_name="EGA" xmlns:xsi="http://www.w3.org/2001/XMLSchema-instance">
      <IDENTIFIERS>
         <PRIMARY_ID>ERR839830</PRIMARY_ID>
         <SUBMITTER_ID namespace="SC">SC_RUN_14780_2#6</SUBMITTER_ID>
      </IDENTIFIERS>
      <EXPERIMENT_REF refname="SC_EXP_14780_2#6" refcenter="SC" accession="ERX919917">
         <IDENTIFIERS>
            <PRIMARY_ID>ERX919917</PRIMARY_ID>
            <SUBMITTER_ID namespace="SC">SC_EXP_14780_2#6</SUBMITTER_ID>
         </IDENTIFIERS>
      </EXPERIMENT_REF>
      <DATA_BLOCK>
         <FILES>
            <FILE filename="14780_2#6.cram.gpg" filetype="cram" checksum_method="MD5" checksum="b90ce81daa509c22140dc27552446a9d" unencrypted_checksum="8a3af9446e4c9e532f03d006e50faf5b"/>
         </FILES>
      </DATA_BLOCK>
   </RUN>
</RUN_SET>