<?xml version = '1.0' encoding = 'UTF-8'?><RUN_SET>
   <RUN alias="SC_RUN_12561_1#11" center_name="SC" accession="ERR834274" broker_name="EGA" xmlns:xsi="http://www.w3.org/2001/XMLSchema-instance">
      <IDENTIFIERS>
         <PRIMARY_ID>ERR834274</PRIMARY_ID>
         <SUBMITTER_ID namespace="SC">SC_RUN_12561_1#11</SUBMITTER_ID>
      </IDENTIFIERS>
      <EXPERIMENT_REF refname="SC_EXP_12561_1#11" refcenter="SC" accession="ERX914361">
         <IDENTIFIERS>
            <PRIMARY_ID>ERX914361</PRIMARY_ID>
            <SUBMITTER_ID namespace="SC">SC_EXP_12561_1#11</SUBMITTER_ID>
         </IDENTIFIERS>
      </EXPERIMENT_REF>
      <DATA_BLOCK>
         <FILES>
            <FILE filename="12561_1#11.cram.gpg" filetype="cram" checksum_method="MD5" checksum="321a51de69461b44d3cb1e06ce7e26ba" unencrypted_checksum="e14b32ac899a14d1edafebc45cd5b89b"/>
         </FILES>
      </DATA_BLOCK>
   </RUN>
</RUN_SET>