<?xml version = '1.0' encoding = 'UTF-8'?><RUN_SET>
   <RUN alias="SC_RUN_12647_1#20" center_name="SC" accession="ERR834388" broker_name="EGA" xmlns:xsi="http://www.w3.org/2001/XMLSchema-instance">
      <IDENTIFIERS>
         <PRIMARY_ID>ERR834388</PRIMARY_ID>
         <SUBMITTER_ID namespace="SC">SC_RUN_12647_1#20</SUBMITTER_ID>
      </IDENTIFIERS>
      <EXPERIMENT_REF refname="SC_EXP_12647_1#20" refcenter="SC" accession="ERX914475">
         <IDENTIFIERS>
            <PRIMARY_ID>ERX914475</PRIMARY_ID>
            <SUBMITTER_ID namespace="SC">SC_EXP_12647_1#20</SUBMITTER_ID>
         </IDENTIFIERS>
      </EXPERIMENT_REF>
      <DATA_BLOCK>
         <FILES>
            <FILE filename="12647_1#20.cram.gpg" filetype="cram" checksum_method="MD5" checksum="976ea9b253cf8c9794f2df432e463803" unencrypted_checksum="0dfaee09bfffaa1508a12b2584645079"/>
         </FILES>
      </DATA_BLOCK>
   </RUN>
</RUN_SET>