<?xml version = '1.0' encoding = 'UTF-8'?><RUN_SET>
   <RUN alias="SC_RUN_14154_7#21" center_name="SC" accession="ERR838791" broker_name="EGA" xmlns:xsi="http://www.w3.org/2001/XMLSchema-instance">
      <IDENTIFIERS>
         <PRIMARY_ID>ERR838791</PRIMARY_ID>
         <SUBMITTER_ID namespace="SC">SC_RUN_14154_7#21</SUBMITTER_ID>
      </IDENTIFIERS>
      <EXPERIMENT_REF refname="SC_EXP_14154_7#21" refcenter="SC" accession="ERX918878">
         <IDENTIFIERS>
            <PRIMARY_ID>ERX918878</PRIMARY_ID>
            <SUBMITTER_ID namespace="SC">SC_EXP_14154_7#21</SUBMITTER_ID>
         </IDENTIFIERS>
      </EXPERIMENT_REF>
      <DATA_BLOCK>
         <FILES>
            <FILE filename="14154_7#21.cram.gpg" filetype="cram" checksum_method="MD5" checksum="a5dd097923ae892c7a2e3c887d9214da" unencrypted_checksum="334cdeae9aa71e180f57390d23def685"/>
         </FILES>
      </DATA_BLOCK>
   </RUN>
</RUN_SET>