<?xml version = '1.0' encoding = 'UTF-8'?><RUN_SET>
   <RUN alias="SC_RUN_11495_2#91" center_name="SC" accession="ERR446189" broker_name="EGA" xmlns:xsi="http://www.w3.org/2001/XMLSchema-instance">
      <IDENTIFIERS>
         <PRIMARY_ID>ERR446189</PRIMARY_ID>
         <SUBMITTER_ID namespace="SC">SC_RUN_11495_2#91</SUBMITTER_ID>
      </IDENTIFIERS>
      <EXPERIMENT_REF refname="SC_EXP_11495_2#91" refcenter="SC" accession="ERX412561">
         <IDENTIFIERS>
            <PRIMARY_ID>ERX412561</PRIMARY_ID>
            <SUBMITTER_ID namespace="SC">SC_EXP_11495_2#91</SUBMITTER_ID>
         </IDENTIFIERS>
      </EXPERIMENT_REF>
      <DATA_BLOCK>
         <FILES>
            <FILE filename="11495_2#91.cram.gpg" filetype="cram" checksum_method="MD5" checksum="92b43ce3e9ddd5b7da7576c2d97e59ab" unencrypted_checksum="85c06a4b8d0e73ab37bc872d9deb1d6c"/>
         </FILES>
      </DATA_BLOCK>
   </RUN>
</RUN_SET>