<?xml version = '1.0' encoding = 'UTF-8'?><RUN_SET>
   <RUN alias="SC_RUN_13041_2#29" center_name="SC" accession="ERR835927" broker_name="EGA" xmlns:xsi="http://www.w3.org/2001/XMLSchema-instance">
      <IDENTIFIERS>
         <PRIMARY_ID>ERR835927</PRIMARY_ID>
         <SUBMITTER_ID namespace="SC">SC_RUN_13041_2#29</SUBMITTER_ID>
      </IDENTIFIERS>
      <EXPERIMENT_REF refname="SC_EXP_13041_2#29" refcenter="SC" accession="ERX916014">
         <IDENTIFIERS>
            <PRIMARY_ID>ERX916014</PRIMARY_ID>
            <SUBMITTER_ID namespace="SC">SC_EXP_13041_2#29</SUBMITTER_ID>
         </IDENTIFIERS>
      </EXPERIMENT_REF>
      <DATA_BLOCK>
         <FILES>
            <FILE filename="13041_2#29.cram.gpg" filetype="cram" checksum_method="MD5" checksum="80d160a652081a0b0faee62bcec428e9" unencrypted_checksum="bf2b51a26160e72329f3c85d81f69247"/>
         </FILES>
      </DATA_BLOCK>
   </RUN>
</RUN_SET>