<?xml version = '1.0' encoding = 'UTF-8'?><RUN_SET>
   <RUN alias="SC_RUN_11905_7#14" center_name="SC" accession="ERR483179" broker_name="EGA" xmlns:xsi="http://www.w3.org/2001/XMLSchema-instance">
      <IDENTIFIERS>
         <PRIMARY_ID>ERR483179</PRIMARY_ID>
         <SUBMITTER_ID namespace="SC">SC_RUN_11905_7#14</SUBMITTER_ID>
      </IDENTIFIERS>
      <EXPERIMENT_REF refname="SC_EXP_11905_7#14" refcenter="SC" accession="ERX449011">
         <IDENTIFIERS>
            <PRIMARY_ID>ERX449011</PRIMARY_ID>
            <SUBMITTER_ID namespace="SC">SC_EXP_11905_7#14</SUBMITTER_ID>
         </IDENTIFIERS>
      </EXPERIMENT_REF>
      <DATA_BLOCK>
         <FILES>
            <FILE filename="11905_7#14.cram.gpg" filetype="cram" checksum_method="MD5" checksum="bf4df19f84781442fb6b5be77811d76b" unencrypted_checksum="341d0249d92d8b518fab0f3236dea9b3"/>
         </FILES>
      </DATA_BLOCK>
   </RUN>
</RUN_SET>