<?xml version = '1.0' encoding = 'UTF-8'?><RUN_SET>
   <RUN alias="SC_RUN_11373_1#53" center_name="SC" accession="ERR431895" broker_name="EGA" xmlns:xsi="http://www.w3.org/2001/XMLSchema-instance">
      <IDENTIFIERS>
         <PRIMARY_ID>ERR431895</PRIMARY_ID>
         <SUBMITTER_ID namespace="SC">SC_RUN_11373_1#53</SUBMITTER_ID>
      </IDENTIFIERS>
      <EXPERIMENT_REF refname="SC_EXP_11373_1#53" refcenter="SC" accession="ERX398170">
         <IDENTIFIERS>
            <PRIMARY_ID>ERX398170</PRIMARY_ID>
            <SUBMITTER_ID namespace="SC">SC_EXP_11373_1#53</SUBMITTER_ID>
         </IDENTIFIERS>
      </EXPERIMENT_REF>
      <DATA_BLOCK>
         <FILES>
            <FILE filename="11373_1#53.cram.gpg" filetype="cram" checksum_method="MD5" checksum="d3607c2d01d6712131a366352c14475a" unencrypted_checksum="7f0c967e399d9a2bd80d0e8386f8e7c9"/>
         </FILES>
      </DATA_BLOCK>
   </RUN>
</RUN_SET>