<?xml version = '1.0' encoding = 'UTF-8'?><RUN_SET>
   <RUN alias="SC_RUN_11376_1#37" center_name="SC" accession="ERR436405" broker_name="EGA" xmlns:xsi="http://www.w3.org/2001/XMLSchema-instance">
      <IDENTIFIERS>
         <PRIMARY_ID>ERR436405</PRIMARY_ID>
         <SUBMITTER_ID namespace="SC">SC_RUN_11376_1#37</SUBMITTER_ID>
      </IDENTIFIERS>
      <EXPERIMENT_REF refname="SC_EXP_11376_1#37" refcenter="SC" accession="ERX403068">
         <IDENTIFIERS>
            <PRIMARY_ID>ERX403068</PRIMARY_ID>
            <SUBMITTER_ID namespace="SC">SC_EXP_11376_1#37</SUBMITTER_ID>
         </IDENTIFIERS>
      </EXPERIMENT_REF>
      <DATA_BLOCK>
         <FILES>
            <FILE filename="11376_1#37.cram.gpg" filetype="cram" checksum_method="MD5" checksum="481ab3bbf9383c7c3095340e2c712a28" unencrypted_checksum="ad9aab33d6bccfd8cef43a2098d7a093"/>
         </FILES>
      </DATA_BLOCK>
   </RUN>
</RUN_SET>