<?xml version = '1.0' encoding = 'UTF-8'?><RUN_SET>
   <RUN alias="SC_RUN_12399_5#26" center_name="SC" accession="ERR555238" broker_name="EGA" xmlns:xsi="http://www.w3.org/2001/XMLSchema-instance">
      <IDENTIFIERS>
         <PRIMARY_ID>ERR555238</PRIMARY_ID>
         <SUBMITTER_ID namespace="SC">SC_RUN_12399_5#26</SUBMITTER_ID>
      </IDENTIFIERS>
      <EXPERIMENT_REF refname="SC_EXP_12399_5#26" refcenter="SC" accession="ERX514307">
         <IDENTIFIERS>
            <PRIMARY_ID>ERX514307</PRIMARY_ID>
            <SUBMITTER_ID namespace="SC">SC_EXP_12399_5#26</SUBMITTER_ID>
         </IDENTIFIERS>
      </EXPERIMENT_REF>
      <DATA_BLOCK>
         <FILES>
            <FILE filename="12399_5#26.cram.gpg" filetype="cram" checksum_method="MD5" checksum="f8022a80ae387d667de960ba9ab7589b" unencrypted_checksum="089068337f49b6c60736f0f29c4cb8ea"/>
         </FILES>
      </DATA_BLOCK>
   </RUN>
</RUN_SET>