<?xml version = '1.0' encoding = 'UTF-8'?><RUN_SET>
   <RUN alias="SC_RUN_11531_2#24" center_name="SC" accession="ERR446333" broker_name="EGA" xmlns:xsi="http://www.w3.org/2001/XMLSchema-instance">
      <IDENTIFIERS>
         <PRIMARY_ID>ERR446333</PRIMARY_ID>
         <SUBMITTER_ID namespace="SC">SC_RUN_11531_2#24</SUBMITTER_ID>
      </IDENTIFIERS>
      <EXPERIMENT_REF refname="SC_EXP_11531_2#24" refcenter="SC" accession="ERX412705">
         <IDENTIFIERS>
            <PRIMARY_ID>ERX412705</PRIMARY_ID>
            <SUBMITTER_ID namespace="SC">SC_EXP_11531_2#24</SUBMITTER_ID>
         </IDENTIFIERS>
      </EXPERIMENT_REF>
      <DATA_BLOCK>
         <FILES>
            <FILE filename="11531_2#24.cram.gpg" filetype="cram" checksum_method="MD5" checksum="5e11b26ae191a3d62713f2de48b7e521" unencrypted_checksum="3c49194096d918d793c7be838c0ba787"/>
         </FILES>
      </DATA_BLOCK>
   </RUN>
</RUN_SET>