<?xml version = '1.0' encoding = 'UTF-8'?><RUN_SET>
   <RUN alias="SC_RUN_10751_7#4" center_name="SC" accession="ERR401021" broker_name="EGA" xmlns:xsi="http://www.w3.org/2001/XMLSchema-instance">
      <IDENTIFIERS>
         <PRIMARY_ID>ERR401021</PRIMARY_ID>
         <SUBMITTER_ID namespace="SC">SC_RUN_10751_7#4</SUBMITTER_ID>
      </IDENTIFIERS>
      <EXPERIMENT_REF refname="SC_EXP_10751_7#4" refcenter="SC" accession="ERX367382">
         <IDENTIFIERS>
            <PRIMARY_ID>ERX367382</PRIMARY_ID>
            <SUBMITTER_ID namespace="SC">SC_EXP_10751_7#4</SUBMITTER_ID>
         </IDENTIFIERS>
      </EXPERIMENT_REF>
      <DATA_BLOCK>
         <FILES>
            <FILE filename="10751_7#4.cram.gpg" filetype="cram" checksum_method="MD5" checksum="445dcfe1a676c546778a1db4b8850563" unencrypted_checksum="85123059d46f73cd8a9066193083a054"/>
         </FILES>
      </DATA_BLOCK>
   </RUN>
</RUN_SET>